[
  {
    "name": "Abdul Mustafa",
    "email": "abdul.mustafa@example.com",
    "code": "8LZULM"
  },
  {
    "name": "Hafiza Sadia Saeed",
    "email": "hafiza.sadia@example.com",
    "code": "QBLKSS"
  },
  {
    "name": "Muhammad Naveed Asghar",
    "email": "naveed.asghar@example.com",
    "code": "7WU43N"
  },
  {
    "name": "Muhammad Jawad Baig",
    "email": "jawad.baig@example.com",
    "code": "JJ264B"
  },
  {
    "name": "Muhammad Sameer Ur Rehman",
    "email": "sameer.rehman@example.com",
    "code": "153R0Q"
  },
  {
    "name": "Muhammad Attar",
    "email": "muhammad.attar@example.com",
    "code": "FJW8JI"
  },
  {
    "name": "Muhammad Hamza",
    "email": "muhammad.hamza@example.com",
    "code": "I33SYN"
  },
  {
    "name": "Ali Haider",
    "email": "ali.haider@example.com",
    "code": "UGNSNG"
  },
  {
    "name": "Shaista Raza",
    "email": "shaista.raza@example.com",
    "code": "G7WWNQ"
  },
  {
    "name": "Muhammad Abid Jamal",
    "email": "abid.jamal@example.com",
    "code": "RGSTOM"
  },
  {
    "name": "Ahsan Ali",
    "email": "ahsan.ali@example.com",
    "code": "GWZH2Y"
  },
  {
    "name": "Abdullah Aslam",
    "email": "abdullah.aslam@example.com",
    "code": "66NV8F"
  },
  {
    "name": "Muhammad Tahir Hussain Qazi",
    "email": "tahir.qazi@example.com",
    "code": "FPZNDL"
  },
  {
    "name": "Muhammad Junaid",
    "email": "muhammad.junaid@example.com",
    "code": "C790KT"
  },
  {
    "name": "Muhammad Zubair Afzal",
    "email": "zubair.afzal@example.com",
    "code": "JB7B1X"
  },
  {
    "name": "Sikandar Ali",
    "email": "sikandar.ali@example.com",
    "code": "NHD970"
  },
  {
    "name": "Babar Ali",
    "email": "babar.ali@example.com",
    "code": "LVCV7E"
  },
  {
    "name": "Ali Hussain",
    "email": "ali.hussain@example.com",
    "code": "W3B7AV"
  },
  {
    "name": "Testing Student",
    "email": "testing.student@example.com",
    "code": "11SNM3"
  }
]
